CHANGELOG.md
LICENSE
MANIFEST.in
README.rst
setup.py
django_whoshere/__init__.py
django_whoshere/admin.py
django_whoshere/apps.py
django_whoshere/middleware.py
django_whoshere/models.py
django_whoshere.egg-info/PKG-INFO
django_whoshere.egg-info/SOURCES.txt
django_whoshere.egg-info/dependency_links.txt
django_whoshere.egg-info/pbr.json
django_whoshere.egg-info/requires.txt
django_whoshere.egg-info/top_level.txt
django_whoshere/migrations/0001_initial.py
django_whoshere/migrations/__init__.py
django_whoshere/templatetags/__init__.py
django_whoshere/templatetags/whoshere.py
django_whoshere/tests/__init__.py
django_whoshere/tests/runtests.py
django_whoshere/tests/settings.py
django_whoshere/tests/tests.py
django_whoshere/tests/urls.py